{
  "sections": {
    "image_banner": {
      "type": "image-banner",
      "blocks": {
        "text": {
          "type": "text",
          "settings": {
            "text": "Natural Skin Care",
            "text_style": "subtitle"
          }
        },
        "heading": {
          "type": "heading",
          "settings": {
            "heading": "Effortless Beauty",
            "heading_size": "h0"
          }
        },
        "button": {
          "type": "buttons",
          "settings": {
            "button_label_1": "Shop Skin Care",
            "button_link_1": "shopify:\/\/collections\/all",
            "button_style_secondary_1": false,
            "button_label_2": "",
            "button_link_2": "",
            "button_style_secondary_2": false
          }
        }
      },
      "block_order": [
        "text",
        "heading",
        "button"
      ],
      "settings": {
        "image": "shopify:\/\/shop_images\/b_bright_clay_mask_papaya.jpg",
        "image_overlay_opacity": 20,
        "image_height": "small",
        "adapt_height_first_image": false,
        "desktop_content_position": "bottom-center",
        "show_text_box": false,
        "desktop_content_alignment": "center",
        "color_scheme": "background-1",
        "mobile_content_alignment": "center",
        "stack_images_on_mobile": false,
        "show_text_below": false
      }
    },
    "3197dca7-35b4-444c-9282-a15f82d26178": {
      "type": "icons-section",
      "blocks": {
        "f09a898d-9e7a-4774-a589-f73e68b83fa3": {
          "type": "icon",
          "settings": {
            "image": "shopify:\/\/shop_images\/skincare.png",
            "title": "Moisturizes naturally",
            "width": 68
          }
        },
        "e8c03161-7cdb-48f7-9182-b84d85ce1f3c": {
          "type": "icon",
          "settings": {
            "image": "shopify:\/\/shop_images\/skincare-2.png",
            "title": "Repairs your skin barrier",
            "width": 68
          }
        },
        "870b0fbb-07c5-4056-8556-cba4f7aaf4ba": {
          "type": "icon",
          "settings": {
            "image": "shopify:\/\/shop_images\/ph-balance.png",
            "title": "Perfect for sensitive skin",
            "width": 64
          }
        }
      },
      "block_order": [
        "f09a898d-9e7a-4774-a589-f73e68b83fa3",
        "e8c03161-7cdb-48f7-9182-b84d85ce1f3c",
        "870b0fbb-07c5-4056-8556-cba4f7aaf4ba"
      ],
      "settings": {
        "title": "",
        "background-color": "#ffecb3"
      }
    },
    "2f398fb8-3456-477b-a06a-5b7846e4a5e2": {
      "type": "featured-products-carousel",
      "settings": {
        "title": "",
        "product": "bright-tight-and-smooth-honey-mask",
        "collection": "body-1",
        "show_reviews": true,
        "url": "shopify:\/\/collections\/best-sellers",
        "link_text": "Shop Best Sellers"
      }
    },
    "dbd1826b-27c3-4d32-9e45-45e3478b1a19": {
      "type": "icons-section",
      "blocks": {
        "50c3a372-50c2-41e1-a3d8-f1e36b3575b8": {
          "type": "icon",
          "settings": {
            "image": "shopify:\/\/shop_images\/water.png",
            "title": "Hand-made, small batch",
            "width": 68
          }
        },
        "7bdd001f-3064-4f5e-8bc0-7cf5f53c5897": {
          "type": "icon",
          "settings": {
            "image": "shopify:\/\/shop_images\/anti-age.png",
            "title": "Remove makeup easily",
            "width": 68
          }
        },
        "ac68d238-a5ab-4f0f-ae8a-c513c5105854": {
          "type": "icon",
          "settings": {
            "image": "shopify:\/\/shop_images\/collagen.png",
            "title": "Made with local, raw honey",
            "width": 68
          }
        }
      },
      "block_order": [
        "50c3a372-50c2-41e1-a3d8-f1e36b3575b8",
        "7bdd001f-3064-4f5e-8bc0-7cf5f53c5897",
        "ac68d238-a5ab-4f0f-ae8a-c513c5105854"
      ],
      "settings": {
        "title": "",
        "background-color": "#ffecb3"
      }
    },
    "e3b8da4c-33f0-498f-a917-b32966b9a4bb": {
      "type": "ugc-reviews",
      "blocks": {
        "cbeb2641-3ba0-4886-9832-840ccf9fae6f": {
          "type": "review",
          "settings": {
            "name": "Shalya",
            "image": "shopify:\/\/shop_images\/shaylyn.png",
            "content": ""
          }
        },
        "7b8b5ea2-af11-44a0-b5d1-8dddfb696ed2": {
          "type": "review",
          "settings": {
            "name": "Audra",
            "image": "shopify:\/\/shop_images\/audra.png",
            "content": ""
          }
        }
      },
      "block_order": [
        "cbeb2641-3ba0-4886-9832-840ccf9fae6f",
        "7b8b5ea2-af11-44a0-b5d1-8dddfb696ed2"
      ],
      "settings": {
        "title": "Reviews",
        "caption": "What our customers say",
        "description": "We love our customers and they love us back. Here are some of the kind words they have to say about us."
      }
    },
    "cefdaed6-4ea3-4334-a6f9-cef305beb1ab": {
      "type": "clean-b-feature",
      "blocks": {
        "6351a4a4-1924-4086-9a8b-fb547b57bc3e": {
          "type": "rating",
          "settings": {
          }
        },
        "3dcac312-04bc-4d9d-b1d3-e38725758e41": {
          "type": "caption",
          "settings": {
            "caption": "4 Steps. 5 minutes. Skin Care Simplified."
          }
        },
        "512cca96-588c-4fb9-a868-02c845b8a568": {
          "type": "heading",
          "settings": {
            "heading": "It's easy, honey"
          }
        },
        "9d237e05-635e-46ff-a6e5-5a816aee1d35": {
          "type": "price",
          "settings": {
            "compare_at": true
          }
        },
        "57410610-3c7e-4cc4-9e5e-c7e121e3def4": {
          "type": "rich_text",
          "settings": {
            "text": "<p>Fugiat irure voluptate qui adipisicing et enim ex ullamco sit magna amet nostrud.<\/p>"
          }
        },
        "befbcfb8-2c64-4537-a388-bd51c99040eb": {
          "type": "step",
          "settings": {
            "title": "Cleanse"
          }
        },
        "03d556c7-9753-4f5f-b16f-f0e91f54ff61": {
          "type": "step",
          "settings": {
            "title": "Clarify"
          }
        },
        "8a9763db-17e3-4fca-9d6a-2b25fa841380": {
          "type": "step",
          "settings": {
            "title": "Tone"
          }
        },
        "43fc8387-f62a-46fd-b686-e56b28fdf10a": {
          "type": "step",
          "settings": {
            "title": "Moisturize"
          }
        }
      },
      "block_order": [
        "6351a4a4-1924-4086-9a8b-fb547b57bc3e",
        "3dcac312-04bc-4d9d-b1d3-e38725758e41",
        "512cca96-588c-4fb9-a868-02c845b8a568",
        "9d237e05-635e-46ff-a6e5-5a816aee1d35",
        "57410610-3c7e-4cc4-9e5e-c7e121e3def4",
        "befbcfb8-2c64-4537-a388-bd51c99040eb",
        "03d556c7-9753-4f5f-b16f-f0e91f54ff61",
        "8a9763db-17e3-4fca-9d6a-2b25fa841380",
        "43fc8387-f62a-46fd-b686-e56b28fdf10a"
      ],
      "settings": {
        "product": "clean-b-cleansing-trio-2-oz-travel-sizes",
        "video": "shopify:\/\/files\/videos\/OiWm7wdWhCDOZilzxuzgwh4tYi8_3npkeq6GDQBAWeSYKuF-CYSIO2vkqcAJz4CMjfSjxx0.mp4",
        "show_button": true
      }
    },
    "034248a6-55a1-425c-a656-1e456506eca1": {
      "type": "ingredients-feature",
      "blocks": {
        "1a9683d2-3817-40b1-a01b-ef85aa898a96": {
          "type": "ingredient",
          "settings": {
            "ingredient_name": "Ingredient Name"
          }
        },
        "36d1be97-c4a9-4b0d-a117-0fd2bb001b43": {
          "type": "ingredient",
          "settings": {
            "ingredient_name": "Ingredient Name"
          }
        },
        "7dba9037-c088-41d2-9a6d-c32b16834d5b": {
          "type": "ingredient",
          "settings": {
            "ingredient_name": "Ingredient Name"
          }
        },
        "7c2d9f89-edee-4a38-8157-0fac005bdee1": {
          "type": "ingredient",
          "settings": {
            "ingredient_name": "Ingredient Name"
          }
        },
        "55be750f-6a4a-4bf2-a149-2b53a28596fc": {
          "type": "ingredient",
          "settings": {
            "ingredient_name": "Ingredient Name"
          }
        }
      },
      "block_order": [
        "1a9683d2-3817-40b1-a01b-ef85aa898a96",
        "36d1be97-c4a9-4b0d-a117-0fd2bb001b43",
        "7dba9037-c088-41d2-9a6d-c32b16834d5b",
        "7c2d9f89-edee-4a38-8157-0fac005bdee1",
        "55be750f-6a4a-4bf2-a149-2b53a28596fc"
      ],
      "settings": {
        "caption": "What's inside?",
        "title": "Clean Ingredients For Clear Skin",
        "description": ""
      }
    },
    "ed88ccd3-9157-49de-9498-d52bca9e524d": {
      "type": "buy-section",
      "blocks": {
        "template--16684277858548__ed88ccd3-9157-49de-9498-d52bca9e524d-16753613860f600ba7-0": {
          "type": "caption",
          "settings": {
            "text": "The Clean B Routine"
          }
        },
        "template--16684277858548__ed88ccd3-9157-49de-9498-d52bca9e524d-16753613860f600ba7-1": {
          "type": "heading",
          "settings": {
            "text": "Be On Your Way To Clear Skin in 5 Minutes A Day"
          }
        },
        "46f6e332-03b8-490b-8392-9e417abdf149": {
          "type": "price",
          "settings": {
            "compare_at": true
          }
        },
        "82c2b285-415c-4a46-a987-ee9b59fab7bd": {
          "type": "button",
          "settings": {
            "text": "This is a button",
            "url": "\/"
          }
        }
      },
      "block_order": [
        "template--16684277858548__ed88ccd3-9157-49de-9498-d52bca9e524d-16753613860f600ba7-0",
        "template--16684277858548__ed88ccd3-9157-49de-9498-d52bca9e524d-16753613860f600ba7-1",
        "46f6e332-03b8-490b-8392-9e417abdf149",
        "82c2b285-415c-4a46-a987-ee9b59fab7bd"
      ],
      "settings": {
        "product": "clean-b-collection-bundle"
      }
    },
    "e3c83ced-2cf0-46ab-bf25-6163d09d015d": {
      "type": "image-banner",
      "blocks": {
        "template--16684277858548__e3c83ced-2cf0-46ab-bf25-6163d09d015d-1675361686aac79c86-0": {
          "type": "heading",
          "settings": {
            "heading": "Have a question?",
            "heading_size": "h2"
          }
        },
        "template--16684277858548__e3c83ced-2cf0-46ab-bf25-6163d09d015d-1675361686aac79c86-2": {
          "type": "buttons",
          "settings": {
            "button_label_1": "Ask Us Anything!",
            "button_link_1": "shopify:\/\/pages\/contact",
            "button_style_secondary_1": false,
            "button_label_2": "",
            "button_link_2": "",
            "button_style_secondary_2": false
          }
        }
      },
      "block_order": [
        "template--16684277858548__e3c83ced-2cf0-46ab-bf25-6163d09d015d-1675361686aac79c86-0",
        "template--16684277858548__e3c83ced-2cf0-46ab-bf25-6163d09d015d-1675361686aac79c86-2"
      ],
      "settings": {
        "image": "shopify:\/\/shop_images\/4_piece_bundle_13.jpg",
        "image_overlay_opacity": 10,
        "image_height": "small",
        "adapt_height_first_image": false,
        "desktop_content_position": "middle-center",
        "show_text_box": false,
        "desktop_content_alignment": "center",
        "color_scheme": "background-1",
        "mobile_content_alignment": "center",
        "stack_images_on_mobile": true,
        "show_text_below": false
      }
    },
    "596110af-7a44-4fdf-81d3-fb9b5db36c54": {
      "type": "our-promise",
      "blocks": {
        "97cbfd00-78cd-4275-8fc1-a31383e44c85": {
          "type": "caption",
          "settings": {
            "text": "Our Promise To You"
          }
        },
        "c465dba0-aee1-4849-ad28-13a4b5fb1d17": {
          "type": "heading",
          "settings": {
            "text": "Clean, Affordable Skincare, For Everyone."
          }
        },
        "ebe85f31-c367-449a-9224-0bd0a1d60b56": {
          "type": "icon_block",
          "settings": {
            "title": "High Quality Ingredients",
            "text": "We know our suppliers, most are local!",
            "image": "shopify:\/\/shop_images\/cell_1.png"
          }
        },
        "fc2b8a6f-93b8-48e0-a1f5-885bf50d846f": {
          "type": "icon_block",
          "settings": {
            "title": "Esthetician Approved",
            "text": "Used daily in Alicia's esthetician practice",
            "image": "shopify:\/\/shop_images\/eyebrow.png"
          }
        },
        "f8842b49-416b-4744-882f-7e2b4341a257": {
          "type": "icon_block",
          "settings": {
            "title": "Environmentally Conscious",
            "text": "Sustainably sourced and packaged.",
            "image": "shopify:\/\/shop_images\/charity.png"
          }
        },
        "ebe5157a-0e65-49bf-8e57-e68cff6711fe": {
          "type": "paragraph",
          "settings": {
            "text": "<p>We founded Essentially Haitos after creating the Bright, Tight & Smooth Honey Mask to help Alicia conquer acne. <\/p><p><\/p><p>As an esthetician, Alicia uses our products every day in her practice. <\/p><p><\/p><p>We've continued to develop innovative skin care at an affordable price, because everyone deserves the confidence of clear skin.<\/p>"
          }
        }
      },
      "block_order": [
        "97cbfd00-78cd-4275-8fc1-a31383e44c85",
        "c465dba0-aee1-4849-ad28-13a4b5fb1d17",
        "ebe85f31-c367-449a-9224-0bd0a1d60b56",
        "fc2b8a6f-93b8-48e0-a1f5-885bf50d846f",
        "f8842b49-416b-4744-882f-7e2b4341a257",
        "ebe5157a-0e65-49bf-8e57-e68cff6711fe"
      ],
      "settings": {
        "image": "shopify:\/\/shop_images\/KarenAliciaFinals_136_2_2x_8470f6cc-0ed0-402d-8ee3-b68ab67ce1ab.jpg"
      }
    },
    "e06dbbf4-4ef4-4a53-bcf3-28dcdea7916b": {
      "type": "featured-products-carousel",
      "settings": {
        "title": "",
        "product": "clean-b-cleansing-trio",
        "collection": "clean-b",
        "show_reviews": true,
        "url": "",
        "link_text": ""
      }
    },
    "1675145644c97bf3fe": {
      "type": "apps",
      "disabled": true,
      "blocks": {
        "06ff8310-7ae0-42b5-98f6-e7c0ddd4d132": {
          "type": "shopify:\/\/apps\/instafeed-instagram-feed\/blocks\/app-block\/c447db20-095d-4a10-9725-b5977662c9d5",
          "settings": {
            "heading_size": 20,
            "feed_width": 100,
            "html_area": ""
          }
        }
      },
      "block_order": [
        "06ff8310-7ae0-42b5-98f6-e7c0ddd4d132"
      ],
      "settings": {
        "include_margins": true
      }
    }
  },
  "order": [
    "image_banner",
    "3197dca7-35b4-444c-9282-a15f82d26178",
    "2f398fb8-3456-477b-a06a-5b7846e4a5e2",
    "dbd1826b-27c3-4d32-9e45-45e3478b1a19",
    "e3b8da4c-33f0-498f-a917-b32966b9a4bb",
    "cefdaed6-4ea3-4334-a6f9-cef305beb1ab",
    "034248a6-55a1-425c-a656-1e456506eca1",
    "ed88ccd3-9157-49de-9498-d52bca9e524d",
    "e3c83ced-2cf0-46ab-bf25-6163d09d015d",
    "596110af-7a44-4fdf-81d3-fb9b5db36c54",
    "e06dbbf4-4ef4-4a53-bcf3-28dcdea7916b",
    "1675145644c97bf3fe"
  ]
}